sql_ingest_util/__init__.py
sql_ingest_util/sql_ingest_configs.py
sql_ingest_util/validate_configs.py
sql_ingest_util/utils/__init__.py
sql_ingest_util/utils/yaml_config_convertor.py
sql_ingest_util-0.5.dist-info/METADATA
sql_ingest_util-0.5.dist-info/WHEEL
sql_ingest_util-0.5.dist-info/top_level.txt
sql_ingest_util-0.5.dist-info/RECORD
